pytidyverse/__init__.py
pytidyverse-0.0.1.dev1.dist-info/METADATA
pytidyverse-0.0.1.dev1.dist-info/WHEEL
pytidyverse-0.0.1.dev1.dist-info/top_level.txt
pytidyverse-0.0.1.dev1.dist-info/RECORD
