Metadata-Version: 2.1
Name: pytidyverse
Version: 0.0.1.dev1
Summary: A simple python wrapper to easily import packages that were designed to syntactically mimic the R tidyverse
Home-page: https://github.com/durrantmm/pytidyverse
Author: Matt Durrant
Author-email: matthewgeorgedurrant@gmail.com
License: UNKNOWN
Keywords: tidyverse dplython dplyr tidypython tidyr ggplot readr readpy R syntax
Platform: UNKNOWN
Requires-Dist: dplython
Requires-Dist: ggplot
Requires-Dist: tidypython
Requires-Dist: readpy
